damv1myparamikossh/__init__.py
damv1myparamikossh/myparamiko.py
damv1myparamikossh-0.0.8.dist-info/METADATA
damv1myparamikossh-0.0.8.dist-info/WHEEL
damv1myparamikossh-0.0.8.dist-info/top_level.txt
damv1myparamikossh-0.0.8.dist-info/RECORD
